<?xml version="1.0" encoding="UTF-8" ?>
<!DOCTYPE mapper PUBLIC "-//mybatis.org//DTD Mapper 3.0//EN" "http://mybatis.org/dtd/mybatis-3-mapper.dtd" >
<mapper namespace="com.bdcor.pip.web.data.dao.PipCommDictDistrictMapper" >
  <resultMap id="BaseResultMap" type="com.bdcor.pip.web.data.domain.PipCommDictDistrict" >
    <!--
      WARNING - @mbggenerated
      This element is automatically generated by MyBatis Generator, do not modify.
    -->
    <result column="DICT_CODE" property="dictCode" jdbcType="VARCHAR" />
    <result column="VCODE" property="vcode" jdbcType="VARCHAR" />
    <result column="VNAME" property="vname" jdbcType="VARCHAR" />
    <result column="CREATE_BY" property="createBy" jdbcType="VARCHAR" />
    <result column="CREATE_DATE" property="createDate" jdbcType="TIMESTAMP" />
    <result column="UPDATE_BY" property="updateBy" jdbcType="VARCHAR" />
    <result column="UPDATE_DATE" property="updateDate" jdbcType="TIMESTAMP" />
    <result column="IS_REMOVED" property="isRemoved" jdbcType="DECIMAL" />
    <result column="ID" property="id" jdbcType="VARCHAR" />
  </resultMap>
  <sql id="Example_Where_Clause" >
    <!--
      WARNING - @mbggenerated
      This element is automatically generated by MyBatis Generator, do not modify.
    -->
    <where >
      <foreach collection="oredCriteria" item="criteria" separator="or" >
        <if test="criteria.valid" >
          <trim prefix="(" suffix=")" prefixOverrides="and" >
            <foreach collection="criteria.criteria" item="criterion" >
              <choose >
                <when test="criterion.noValue" >
                  and ${criterion.condition}
                </when>
                <when test="criterion.singleValue" >
                  and ${criterion.condition} #{criterion.value}
                </when>
                <when test="criterion.betweenValue" >
                  and ${criterion.condition} #{criterion.value} and #{criterion.secondValue}
                </when>
                <when test="criterion.listValue" >
                  and ${criterion.condition}
                  <foreach collection="criterion.value" item="listItem" open="(" close=")" separator="," >
                    #{listItem}
                  </foreach>
                </when>
              </choose>
            </foreach>
          </trim>
        </if>
      </foreach>
    </where>
  </sql>
  <sql id="Update_By_Example_Where_Clause" >
    <!--
      WARNING - @mbggenerated
      This element is automatically generated by MyBatis Generator, do not modify.
    -->
    <where >
      <foreach collection="example.oredCriteria" item="criteria" separator="or" >
        <if test="criteria.valid" >
          <trim prefix="(" suffix=")" prefixOverrides="and" >
            <foreach collection="criteria.criteria" item="criterion" >
              <choose >
                <when test="criterion.noValue" >
                  and ${criterion.condition}
                </when>
                <when test="criterion.singleValue" >
                  and ${criterion.condition} #{criterion.value}
                </when>
                <when test="criterion.betweenValue" >
                  and ${criterion.condition} #{criterion.value} and #{criterion.secondValue}
                </when>
                <when test="criterion.listValue" >
                  and ${criterion.condition}
                  <foreach collection="criterion.value" item="listItem" open="(" close=")" separator="," >
                    #{listItem}
                  </foreach>
                </when>
              </choose>
            </foreach>
          </trim>
        </if>
      </foreach>
    </where>
  </sql>
  <sql id="Base_Column_List" >
    <!--
      WARNING - @mbggenerated
      This element is automatically generated by MyBatis Generator, do not modify.
    -->
    DICT_CODE, VCODE, VNAME, CREATE_BY, CREATE_DATE, UPDATE_BY, UPDATE_DATE, IS_REMOVED, 
    ID
  </sql>
  <select id="selectByExample" resultMap="BaseResultMap" parameterType="com.bdcor.pip.web.data.domain.PipCommDictDistrictExample" >
    <!--
      WARNING - @mbggenerated
      This element is automatically generated by MyBatis Generator, do not modify.
    -->
    select
    <if test="distinct" >
      distinct
    </if>
    <include refid="Base_Column_List" />
    from PIP_COMM_DICT_DISTRICT
    <if test="_parameter != null" >
      <include refid="Example_Where_Clause" />
    </if>
    <if test="orderByClause != null" >
      order by ${orderByClause}
    </if>
  </select>
  <delete id="deleteByExample" parameterType="com.bdcor.pip.web.data.domain.PipCommDictDistrictExample" >
    <!--
      WARNING - @mbggenerated
      This element is automatically generated by MyBatis Generator, do not modify.
    -->
    delete from PIP_COMM_DICT_DISTRICT
    <if test="_parameter != null" >
      <include refid="Example_Where_Clause" />
    </if>
  </delete>
  <insert id="insert" parameterType="com.bdcor.pip.web.data.domain.PipCommDictDistrict" >
    <!--
      WARNING - @mbggenerated
      This element is automatically generated by MyBatis Generator, do not modify.
    -->
    insert into PIP_COMM_DICT_DISTRICT (DICT_CODE, VCODE, VNAME, 
      CREATE_BY, CREATE_DATE, UPDATE_BY, 
      UPDATE_DATE, IS_REMOVED, ID
      )
    values (#{dictCode,jdbcType=VARCHAR}, #{vcode,jdbcType=VARCHAR}, #{vname,jdbcType=VARCHAR}, 
      #{createBy,jdbcType=VARCHAR}, #{createDate,jdbcType=TIMESTAMP}, #{updateBy,jdbcType=VARCHAR}, 
      #{updateDate,jdbcType=TIMESTAMP}, #{isRemoved,jdbcType=DECIMAL}, #{id,jdbcType=VARCHAR}
      )
  </insert>
  <insert id="insertSelective" parameterType="com.bdcor.pip.web.data.domain.PipCommDictDistrict" >
    <!--
      WARNING - @mbggenerated
      This element is automatically generated by MyBatis Generator, do not modify.
    -->
    insert into PIP_COMM_DICT_DISTRICT
    <trim prefix="(" suffix=")" suffixOverrides="," >
      <if test="dictCode != null" >
        DICT_CODE,
      </if>
      <if test="vcode != null" >
        VCODE,
      </if>
      <if test="vname != null" >
        VNAME,
      </if>
      <if test="createBy != null" >
        CREATE_BY,
      </if>
      <if test="createDate != null" >
        CREATE_DATE,
      </if>
      <if test="updateBy != null" >
        UPDATE_BY,
      </if>
      <if test="updateDate != null" >
        UPDATE_DATE,
      </if>
      <if test="isRemoved != null" >
        IS_REMOVED,
      </if>
      <if test="id != null" >
        ID,
      </if>
    </trim>
    <trim prefix="values (" suffix=")" suffixOverrides="," >
      <if test="dictCode != null" >
        #{dictCode,jdbcType=VARCHAR},
      </if>
      <if test="vcode != null" >
        #{vcode,jdbcType=VARCHAR},
      </if>
      <if test="vname != null" >
        #{vname,jdbcType=VARCHAR},
      </if>
      <if test="createBy != null" >
        #{createBy,jdbcType=VARCHAR},
      </if>
      <if test="createDate != null" >
        #{createDate,jdbcType=TIMESTAMP},
      </if>
      <if test="updateBy != null" >
        #{updateBy,jdbcType=VARCHAR},
      </if>
      <if test="updateDate != null" >
        #{updateDate,jdbcType=TIMESTAMP},
      </if>
      <if test="isRemoved != null" >
        #{isRemoved,jdbcType=DECIMAL},
      </if>
      <if test="id != null" >
        #{id,jdbcType=VARCHAR},
      </if>
    </trim>
  </insert>
  <select id="countByExample" parameterType="com.bdcor.pip.web.data.domain.PipCommDictDistrictExample" resultType="java.lang.Integer" >
    <!--
      WARNING - @mbggenerated
      This element is automatically generated by MyBatis Generator, do not modify.
    -->
    select count(*) from PIP_COMM_DICT_DISTRICT
    <if test="_parameter != null" >
      <include refid="Example_Where_Clause" />
    </if>
  </select>
  <update id="updateByExampleSelective" parameterType="map" >
    <!--
      WARNING - @mbggenerated
      This element is automatically generated by MyBatis Generator, do not modify.
    -->
    update PIP_COMM_DICT_DISTRICT
    <set >
      <if test="record.dictCode != null" >
        DICT_CODE = #{record.dictCode,jdbcType=VARCHAR},
      </if>
      <if test="record.vcode != null" >
        VCODE = #{record.vcode,jdbcType=VARCHAR},
      </if>
      <if test="record.vname != null" >
        VNAME = #{record.vname,jdbcType=VARCHAR},
      </if>
      <if test="record.createBy != null" >
        CREATE_BY = #{record.createBy,jdbcType=VARCHAR},
      </if>
      <if test="record.createDate != null" >
        CREATE_DATE = #{record.createDate,jdbcType=TIMESTAMP},
      </if>
      <if test="record.updateBy != null" >
        UPDATE_BY = #{record.updateBy,jdbcType=VARCHAR},
      </if>
      <if test="record.updateDate != null" >
        UPDATE_DATE = #{record.updateDate,jdbcType=TIMESTAMP},
      </if>
      <if test="record.isRemoved != null" >
        IS_REMOVED = #{record.isRemoved,jdbcType=DECIMAL},
      </if>
      <if test="record.id != null" >
        ID = #{record.id,jdbcType=VARCHAR},
      </if>
    </set>
    <if test="_parameter != null" >
      <include refid="Update_By_Example_Where_Clause" />
    </if>
  </update>
  <update id="updateByExample" parameterType="map" >
    <!--
      WARNING - @mbggenerated
      This element is automatically generated by MyBatis Generator, do not modify.
    -->
    update PIP_COMM_DICT_DISTRICT
    set DICT_CODE = #{record.dictCode,jdbcType=VARCHAR},
      VCODE = #{record.vcode,jdbcType=VARCHAR},
      VNAME = #{record.vname,jdbcType=VARCHAR},
      CREATE_BY = #{record.createBy,jdbcType=VARCHAR},
      CREATE_DATE = #{record.createDate,jdbcType=TIMESTAMP},
      UPDATE_BY = #{record.updateBy,jdbcType=VARCHAR},
      UPDATE_DATE = #{record.updateDate,jdbcType=TIMESTAMP},
      IS_REMOVED = #{record.isRemoved,jdbcType=DECIMAL},
      ID = #{record.id,jdbcType=VARCHAR}
    <if test="_parameter != null" >
      <include refid="Update_By_Example_Where_Clause" />
    </if>
  </update>
</mapper>